[
  {
    "op": "core/column-removal",
    "columnName": "Column",
    "description": "Remove column Column"
  },
  {
    "op": "core/column-removal",
    "columnName": "positiva_droga",
    "description": "Remove column positiva_droga"
  },
  {
    "op": "core/column-removal",
    "columnName": "coordenada_y_utm",
    "description": "Remove column coordenada_y_utm"
  },
  {
    "op": "core/column-removal",
    "columnName": "coordenada_x_utm",
    "description": "Remove column coordenada_x_utm"
  },
  {
    "op": "core/column-addition",
    "engineConfig": {
      "facets": [],
      "mode": "row-based"
    },
    "baseColumnName": "fecha",
    "expression": "join ([coalesce(cells['fecha'].value,''),coalesce(cells['hora'].value,'')],' ')",
    "onError": "keep-original",
    "newColumnName": "DateTime",
    "columnInsertIndex": 2,
    "description": "Create column DateTime at index 2 based on column fecha using expression join ([coalesce(cells['fecha'].value,''),coalesce(cells['hora'].value,'')],' ')"
  },
  {
    "op": "core/text-transform",
    "engineConfig": {
      "facets": [],
      "mode": "row-based"
    },
    "columnName": "DateTime",
    "expression": "value.toDate()",
    "onError": "keep-original",
    "repeat": false,
    "repeatCount": 10,
    "description": "Text transform on cells in column DateTime using expression value.toDate()"
  },
  {
    "op": "core/column-removal",
    "columnName": "fecha",
    "description": "Remove column fecha"
  },
  {
    "op": "core/column-removal",
    "columnName": "hora",
    "description": "Remove column hora"
  },
  {
    "op": "core/column-addition",
    "engineConfig": {
      "facets": [],
      "mode": "row-based"
    },
    "baseColumnName": "rango_edad",
    "expression": "grel:value.split(\" \")[1].toNumber()",
    "onError": "set-to-blank",
    "newColumnName": "low_age",
    "columnInsertIndex": 10,
    "description": "Create column low_age at index 10 based on column rango_edad using expression grel:value.split(\" \")[1].toNumber()"
  },
  {
    "op": "core/column-addition",
    "engineConfig": {
      "facets": [],
      "mode": "row-based"
    },
    "baseColumnName": "rango_edad",
    "expression": "grel:value.split(\" \")[-2].toNumber()",
    "onError": "set-to-blank",
    "newColumnName": "high_age",
    "columnInsertIndex": 10,
    "description": "Create column high_age at index 10 based on column rango_edad using expression grel:value.split(\" \")[-2].toNumber()"
  },
  {
    "op": "core/column-move",
    "columnName": "low_age",
    "index": 10,
    "description": "Move column low_age to position 10"
  },
  {
    "op": "core/text-transform",
    "engineConfig": {
      "facets": [],
      "mode": "row-based"
    },
    "columnName": "lesividad",
    "expression": "grel:value.substring(0,-2)",
    "onError": "keep-original",
    "repeat": false,
    "repeatCount": 10,
    "description": "Text transform on cells in column lesividad using expression grel:value.substring(0,-2)"
  },
  {
    "op": "core/text-transform",
    "engineConfig": {
      "facets": [],
      "mode": "row-based"
    },
    "columnName": "localizacion",
    "expression": "grel:value.split(',')[0]",
    "onError": "keep-original",
    "repeat": false,
    "repeatCount": 10,
    "description": "Text transform on cells in column localizacion using expression grel:value.split(',')[0]"
  },
  {
    "op": "core/text-transform",
    "engineConfig": {
      "facets": [],
      "mode": "row-based"
    },
    "columnName": "estado_meteorol贸gico",
    "expression": "grel:if(value==null,\"Se desconoce\",value)",
    "onError": "keep-original",
    "repeat": false,
    "repeatCount": 10,
    "description": "Text transform on cells in column estado_meteorol贸gico using expression grel:if(value==null,\"Se desconoce\",value)"
  },
  {
    "op": "core/text-transform",
    "engineConfig": {
      "facets": [],
      "mode": "row-based"
    },
    "columnName": "estado_meteorol贸gico",
    "expression": "grel:value.replace(\"LLuvia\",\"Lluvia\")",
    "onError": "keep-original",
    "repeat": false,
    "repeatCount": 10,
    "description": "Text transform on cells in column estado_meteorol贸gico using expression grel:value.replace(\"LLuvia\",\"Lluvia\")"
  },
  {
    "op": "core/text-transform",
    "engineConfig": {
      "facets": [],
      "mode": "row-based"
    },
    "columnName": "lesividad",
    "expression": "grel:if(value==null,\"0\",value)",
    "onError": "keep-original",
    "repeat": false,
    "repeatCount": 10,
    "description": "Text transform on cells in column lesividad using expression grel:if(value==null,\"0\",value)"
  },
  {
    "op": "core/text-transform",
    "engineConfig": {
      "facets": [],
      "mode": "row-based"
    },
    "columnName": "low_age",
    "expression": "grel:if(value==null,\"NA\",value)",
    "onError": "keep-original",
    "repeat": false,
    "repeatCount": 10,
    "description": "Text transform on cells in column low_age using expression grel:if(value==null,\"NA\",value)"
  },
  {
    "op": "core/text-transform",
    "engineConfig": {
      "facets": [],
      "mode": "row-based"
    },
    "columnName": "high_age",
    "expression": "grel:if(value==null,\"NA\",value)",
    "onError": "keep-original",
    "repeat": false,
    "repeatCount": 10,
    "description": "Text transform on cells in column high_age using expression grel:if(value==null,\"NA\",value)"
  },
  {
    "op": "core/column-addition",
    "engineConfig": {
      "facets": [],
      "mode": "row-based"
    },
    "baseColumnName": "num_expediente",
    "expression": "grel:value+cells[\"tipo_persona\"].value.substring(0,1)+cells[\"sexo\"].value.substring(0,1)+cells[\"lesividad\"].value.substring(0,1)+cells[\"low_age\"].value+cells[\"high_age\"].value",
    "onError": "set-to-blank",
    "newColumnName": "idPersonAccident",
    "columnInsertIndex": 1,
    "description": "Create column idPersonAccident at index 1 based on column num_expediente using expression grel:value+cells[\"tipo_persona\"].value.substring(0,1)+cells[\"sexo\"].value.substring(0,1)+cells[\"lesividad\"].value.substring(0,1)+cells[\"low_age\"].value+cells[\"high_age\"].value"
  }
]